pypgatk/__init__.py
pypgatk/pypgatk_cli.py
pypgatk/cgenomes/__init__.py
pypgatk/cgenomes/cbioportal_downloader.py
pypgatk/cgenomes/cgenomes_proteindb.py
pypgatk/cgenomes/cosmic_downloader.py
pypgatk/cgenomes/models.py
pypgatk/commands/__init__.py
pypgatk/commands/blast_get_position.py
pypgatk/commands/cbioportal_downloader.py
pypgatk/commands/cbioportal_to_proteindb.py
pypgatk/commands/cosmic_downloader.py
pypgatk/commands/cosmic_to_proteindb.py
pypgatk/commands/dnaseq_to_proteindb.py
pypgatk/commands/ensembl_database.py
pypgatk/commands/ensembl_downloader.py
pypgatk/commands/mztab_class_fdr.py
pypgatk/commands/peptide_class_fdr.py
pypgatk/commands/proteindb_decoy.py
pypgatk/commands/threeframe_translation.py
pypgatk/commands/utils.py
pypgatk/commands/validate_peptides.py
pypgatk/commands/vcf_to_proteindb.py
pypgatk/config/__init__.py
pypgatk/config/assemblies_conf.json
pypgatk/config/cbioportal_config.yaml
pypgatk/config/cosmic_config.yaml
pypgatk/config/ensembl_config.yaml
pypgatk/config/ensembl_downloader_config.yaml
pypgatk/config/openms_analysis.yaml
pypgatk/config/protein_decoy.yaml
pypgatk/db/__init__.py
pypgatk/db/digest_mutant_protein.py
pypgatk/db/map_peptide2genome.py
pypgatk/ensembl/__init__.py
pypgatk/ensembl/data_downloader.py
pypgatk/ensembl/ensembl.py
pypgatk/ensembl/exceptions.py
pypgatk/ensembl/models.py
pypgatk/proteogenomics/__init__.py
pypgatk/proteogenomics/blast_get_position.py
pypgatk/proteogenomics/mztab_class_fdr.py
pypgatk/proteogenomics/validate_peptides.py
pypgatk/proteomics/__init__.py
pypgatk/proteomics/models.py
pypgatk/proteomics/openms.py
pypgatk/proteomics/db/__init__.py
pypgatk/proteomics/db/protein_database_decoy.py
pypgatk/tests/__init__.py
pypgatk/tests/classes_tests.py
pypgatk/tests/pypgatk_tests.py
pypgatk/toolbox/__init__.py
pypgatk/toolbox/exceptions.py
pypgatk/toolbox/general.py
pypgatk/toolbox/rest.py
pypgatk-0.0.24.data/scripts/pypgatk_cli.py
pypgatk-0.0.24.dist-info/LICENSE.txt
pypgatk-0.0.24.dist-info/METADATA
pypgatk-0.0.24.dist-info/WHEEL
pypgatk-0.0.24.dist-info/entry_points.txt
pypgatk-0.0.24.dist-info/top_level.txt
pypgatk-0.0.24.dist-info/RECORD
