Metadata-Version: 2.1
Name: pypgatk
Version: 0.0.24
Summary: Python tools for proteogenomics
Home-page: http://github.com/bigbio/py-pgatk
Author: PgAtk Team
Author-email: ypriverol@gmail.com
License: LICENSE.txt
Requires-Python: >=3.6
License-File: LICENSE.txt
Requires-Dist: biopython
Requires-Dist: Click
Requires-Dist: gffutils
Requires-Dist: numpy
Requires-Dist: pandas
Requires-Dist: PyYAML
Requires-Dist: requests
Requires-Dist: simplejson
Requires-Dist: ratelimit
Requires-Dist: pyteomics
Requires-Dist: pathos
Requires-Dist: pybedtools
Requires-Dist: pyopenms
Requires-Dist: matplotlib
Requires-Dist: tqdm
Requires-Dist: pyahocorasick
